napari_argos_archive_reader/__init__.py
napari_argos_archive_reader/_reader.py
napari_argos_archive_reader/argos_archive_reader.py
napari_argos_archive_reader/napari.yaml
napari_argos_archive_reader/synchronize.py
napari_argos_archive_reader/_tests/__init__.py
napari_argos_archive_reader/_tests/test_reader.py
napari_argos_archive_reader-0.0.7.dist-info/LICENSE
napari_argos_archive_reader-0.0.7.dist-info/METADATA
napari_argos_archive_reader-0.0.7.dist-info/WHEEL
napari_argos_archive_reader-0.0.7.dist-info/entry_points.txt
napari_argos_archive_reader-0.0.7.dist-info/top_level.txt
napari_argos_archive_reader-0.0.7.dist-info/RECORD
