Metadata-Version: 2.1
Name: napari-argos-archive-reader
Version: 0.0.7
Summary: A plugin to read Dioptic ARGOS archive files
Home-page: https://github.com/dioptic/napari-argos-archive-reader
Author: Volker Hilsenstein
Author-email: hilsenstein@dioptic.de
License: MIT
Project-URL: Bug Tracker, https://github.com/dioptic/napari-argos-archive-reader/issues
Project-URL: Documentation, https://github.com/dioptic/napari-argos-archive-reader#README.md
Project-URL: Source Code, https://github.com/dioptic/napari-argos-archive-reader
Project-URL: User Support, https://github.com/dioptic/napari-argos-archive-reader/issues
Classifier: Development Status :: 2 - Pre-Alpha
Classifier: Framework :: napari
Classifier: Intended Audience :: Developers
Classifier: License :: OSI Approved :: MIT License
Classifier: Operating System :: OS Independent
Classifier: Programming Language :: Python
Classifier: Programming Language :: Python :: 3
Classifier: Programming Language :: Python :: 3 :: Only
Classifier: Programming Language :: Python :: 3.8
Classifier: Programming Language :: Python :: 3.9
Classifier: Programming Language :: Python :: 3.10
Classifier: Topic :: Scientific/Engineering :: Image Processing
Requires-Python: >=3.9
License-File: LICENSE
Requires-Dist: napari
Requires-Dist: numpy
Requires-Dist: scikit-image
Requires-Dist: pydantic
Requires-Dist: ruamel.yaml
Provides-Extra: testing
Requires-Dist: tox ; extra == 'testing'
Requires-Dist: pytest ; extra == 'testing'
Requires-Dist: pytest-cov ; extra == 'testing'
